system_tray/__init__.py
system_tray/system_tray.py
system_tray/win_taskbar.py
system_tray/import_and_use.py
system_tray/test_user_interactive_system_tray.py
system_tray/test.py
system_tray/taskbar.py
system_tray/test2.py
system_tray/tray2.py
system_tray/wintray.py
system_tray-0.1.3.dist-info/RECORD
system_tray-0.1.3.dist-info/METADATA
system_tray-0.1.3.dist-info/metadata.json
system_tray-0.1.3.dist-info/top_level.txt
system_tray-0.1.3.dist-info/DESCRIPTION.rst
system_tray-0.1.3.dist-info/WHEEL
